{
  "description": "FIFA Game - 微信小游戏原型",
  "packOptions": {
    "ignore": [],
    "include": []
  },
  "setting": {
    "urlCheck": false,
    "es6": true,
    "enhance": true,
    "postcss": false,
    "minified": false,
    "bigPackageSizeSupport": true,
    "compileWorklet": false,
    "uglifyFileName": false,
    "uploadWithSourceMap": true,
    "packNpmManually": false,
    "packNpmRelationList": [],
    "minifyWXSS": true,
    "minifyWXML": true,
    "localPlugins": false,
    "disableUseStrict": false,
    "useCompilerPlugins": false,
    "condition": false,
    "swc": false,
    "disableSWC": true,
    "babelSetting": {
      "ignore": [],
      "disablePlugins": [],
      "outputPath": ""
    }
  },
  "compileType": "miniprogram",
  "libVersion": "3.17.0",
  "appid": "wx2f1ca5d5dcb60217",
  "projectname": "fifagame",
  "condition": {},
  "simulatorPluginLibVersion": {},
  "editorSetting": {}
}